sparkctl/__init__.py
sparkctl/cluster_manager.py
sparkctl/compute_interface.py
sparkctl/compute_interface_factory.py
sparkctl/config.py
sparkctl/exceptions.py
sparkctl/hive.py
sparkctl/loggers.py
sparkctl/models.py
sparkctl/native_compute.py
sparkctl/slurm_compute.py
sparkctl/spark_process_runner.py
sparkctl/system_utils.py
sparkctl/utils.py
sparkctl/cli/sparkctl.py
sparkctl/conf/hive-site.xml.template
sparkctl/conf/log4j2.properties
sparkctl/conf/spark-defaults.conf.template
sparkctl/conf/spark-env.sh
sparkctl/postgres/setup_metastore.sh
sparkctl/postgres/start_container.sh
sparkctl/postgres/stop_container.sh
sparkctl-0.3.0.dist-info/licenses/LICENSE
sparkctl-0.3.0.dist-info/METADATA
sparkctl-0.3.0.dist-info/WHEEL
sparkctl-0.3.0.dist-info/entry_points.txt
sparkctl-0.3.0.dist-info/top_level.txt
sparkctl-0.3.0.dist-info/RECORD
