Metadata-Version: 2.4
Name: sparkctl
Version: 0.3.0
Summary: Orchestrates Spark standalone clusters on HPCs.
Author-email: Daniel Thom <daniel.thom@nrel.gov>
License-Expression: BSD-3-Clause
Project-URL: Documentation, https://github.com/NREL/sparkctl#readme
Project-URL: Issues, https://github.com/NREL/sparkctl/issues
Project-URL: Source, https://github.com/NREL/sparkctl
Classifier: Development Status :: 4 - Beta
Classifier: Programming Language :: Python
Classifier: Programming Language :: Python :: 3.10
Classifier: Programming Language :: Python :: 3.11
Classifier: Programming Language :: Python :: 3.12
Classifier: Programming Language :: Python :: Implementation :: CPython
Classifier: Programming Language :: Python :: Implementation :: PyPy
Requires-Python: <3.14,>=3.11
License-File: LICENSE
Requires-Dist: click<9,>=8.2
Requires-Dist: dynaconf
Requires-Dist: loguru>=0.7.2
Requires-Dist: psutil
Requires-Dist: pydantic<3,>=2.7
Requires-Dist: pyspark-client==4.0.0
Requires-Dist: rich_click
Requires-Dist: rmon>=0.4.0
Requires-Dist: toml
Requires-Dist: types-psutil
Provides-Extra: pyspark
Requires-Dist: pyspark==4.0.0; extra == "pyspark"
Provides-Extra: dev
Requires-Dist: furo; extra == "dev"
Requires-Dist: mypy<2,>=1.13; extra == "dev"
Requires-Dist: myst_parser; extra == "dev"
Requires-Dist: pre-commit; extra == "dev"
Requires-Dist: pytest; extra == "dev"
Requires-Dist: pytest-cov; extra == "dev"
Requires-Dist: requests; extra == "dev"
Requires-Dist: sphinx; extra == "dev"
Requires-Dist: sphinx-click; extra == "dev"
Requires-Dist: sphinx-copybutton; extra == "dev"
Requires-Dist: autodoc_pydantic~=2.0; extra == "dev"
Requires-Dist: sphinx-tabs~=3.4; extra == "dev"
Requires-Dist: types-requests; extra == "dev"
Requires-Dist: types-toml; extra == "dev"
Dynamic: license-file
